libaloha/__init__.py
libaloha/bin/__init__.py
libaloha/bin/check_ip.py
libaloha/cache/__init__.py
libaloha/cache/exceptions.py
libaloha/cache/redis.py
libaloha/django/__init__.py
libaloha/django/views.py
libaloha/markdown/__init__.py
libaloha/network.py
libaloha/settings.py
libaloha/sms.py
libaloha-0.0.2.dist-info/entry_points.txt
libaloha-0.0.2.dist-info/LICENSE
libaloha-0.0.2.dist-info/WHEEL
libaloha-0.0.2.dist-info/METADATA
libaloha-0.0.2.dist-info/RECORD
